<frontier-connect>
   <proxy url="http://cmst0frontier.cern.ch:3128"/>
   <proxy url="http://cmst0frontier.cern.ch:3128"/>
   <proxy url="http://cmst0frontier1.cern.ch:3128"/>
   <proxy url="http://cmst0frontier2.cern.ch:3128"/>
   <server url="http://cmsfrontier.cern.ch:8000/FrontierInt"/>
   <server url="http://cmsfrontier.cern.ch:8000/FrontierInt"/>
   <server url="http://cmsfrontier1.cern.ch:8000/FrontierInt"/>
   <server url="http://cmsfrontier2.cern.ch:8000/FrontierInt"/>
   <server url="http://cmsfrontier3.cern.ch:8000/FrontierInt"/>
   <server url="http://cmsfrontier4.cern.ch:8000/FrontierInt"/>
</frontier-connect>
